{
  "$schema" : "http://wso2.org/json-schema/wso2-data-mapper-v5.0.0/schema#",
  "inputType" : "CSV",
  "id" : "http://wso2jsonschema.org",
  "title" : "root",
  "type" : "array",
  "items" : [ {
    "properties" : {
      "﻿id" : {
        "id" : "http://wso2jsonschema.org/0/﻿id",
        "type" : "string"
      },
      "makh" : {
        "id" : "http://wso2jsonschema.org/0/makh",
        "type" : "string"
      },
      "tenkh" : {
        "id" : "http://wso2jsonschema.org/0/tenkh",
        "type" : "string"
      },
      "diachi" : {
        "id" : "http://wso2jsonschema.org/0/diachi",
        "type" : "string"
      }
    },
    "id" : "http://wso2jsonschema.org/0",
    "type" : "object"
  } ]
}